{
  "name": "ECHO Obsidian v3",
  "description": "Ultra-dark obsidian UI with fixed typing bar and brand-colored action icons.",
  "authors": [
    { "name": "Gostyk" }
  ],
  "spec": 2,
  "semanticColors": {
    "BACKGROUND_BASE_LOW": ["#05050b", "#ffffff"],
    "BACKGROUND_BASE_LOWER": ["#05050b", "#f2f3f5"],
    "BACKGROUND_BASE_LOWEST": ["#04040a", "#ebedef"],

    "BACKGROUND_SURFACE_HIGH": ["#06060f", "#ffffff"],
    "BACKGROUND_SURFACE_HIGHEST": ["#070711", "#ffffff"],

    "BACKGROUND_BRAND": ["#3e42e6", "#3e42e6"],

    
    "CHAT_INPUT_CONTAINER_BACKGROUND": ["#05050b", "#ffffff"],
    "CHAT_TYPING_BACKGROUND": ["#05050b", "#f2f3f5"],
    "TEXT_TYPING_INDICATOR": ["#9aa0b3", "#5c5e66"],

    
    "CHANNEL_LIST_BACKGROUND": ["#05050b", "#f2f3f5"],
    "CHANNEL_LIST_ACTIVE_CHANNEL_BACKGROUND": ["#3e42e622", "#3e42e618"],
    "CHANNEL_LIST_HOVER_CHANNEL_BACKGROUND": ["#3e42e610", "#3e42e608"],

    "CHANNELTEXTAREA_BACKGROUND": ["#06060f", "#ebedef"],

    
    "CONTROL_PRIMARY_BACKGROUND_DEFAULT": ["#3e42e6", "#3e42e6"],
    "CONTROL_PRIMARY_BACKGROUND_ACTIVE": ["#3239bf", "#3239bf"],
    "CONTROL_PRIMARY_TEXT_DEFAULT": ["#ffffff", "#ffffff"],

    
    "ICON_DEFAULT": ["#3e42e6", "#3e42e6"],
    "ICON_HOVER": ["#7478f5", "#3e42e6"],
    "ICON_ACTIVE": ["#8c90ff", "#3e42e6"],

    "INTERACTIVE_NORMAL": ["#3e42e6", "#3e42e6"],
    "INTERACTIVE_HOVER": ["#7478f5", "#3e42e6"],
    "INTERACTIVE_ACTIVE": ["#8c90ff", "#3e42e6"],

    "TEXT_DEFAULT": ["#e8eaf5", "#313338"],
    "TEXT_STRONG": ["#ffffff", "#060607"],
    "TEXT_MUTED": ["#9aa0b3", "#5c5e66"],

    "TEXT_BRAND": ["#8c90ff", "#3e42e6"],
    "TEXT_LINK": ["#8c90ff", "#006be7"],

    "SCROLLBAR_THIN_THUMB": ["#2a2c44", "#c4c9ce"],
    "SCROLLBAR_THIN_TRACK": ["transparent", "transparent"]
  },
  "rawColors": {
    "BRAND_500": "#3e42e6",
    "BRAND_560": "#3239bf",
    "BRAND_360": "#8c90ff",

    "PRIMARY_600": "#05050b",
    "PRIMARY_630": "#04040a",

    "WHITE_500": "#e8eaf5",
    "WHITE_630": "#9aa0b3"
  }
}
